simple_aiogram/__init__.py
simple_aiogram/bot_temp.py
simple_aiogram/cache.py
simple_aiogram/models/__init__.py
simple_aiogram/models/files.py
simple_aiogram/models/keyboard_builder.py
simple_aiogram/models/message.py
simple_aiogram/models/telegram_window.py
simple_aiogram/models/text.py
simple_aiogram-0.1.0b3.dist-info/LICENSE
simple_aiogram-0.1.0b3.dist-info/METADATA
simple_aiogram-0.1.0b3.dist-info/WHEEL
simple_aiogram-0.1.0b3.dist-info/RECORD
