Metadata-Version: 2.3
Name: simple_aiogram
Version: 0.1.0b3
Summary: Simple and universal keyboard/message builder for aiogram bots.
License: MIT
Keywords: telegram,aiogram,bot,keyboard,pydantic
Author: belyankiss
Author-email: belyankiss@gmail.com
Requires-Python: >=3.10
Classifier: Programming Language :: Python :: 3
Classifier: License :: OSI Approved :: MIT License
Classifier: Framework :: AsyncIO
Classifier: Operating System :: OS Independent
Requires-Dist: aiogram (>=3.20.0.post0,<4.0.0)
Requires-Dist: pydantic (>=2.6,<3.0)
Project-URL: Documentation, https://github.com/belyankiss/aiogram_windows#readme
Project-URL: Homepage, https://github.com/belyankiss/aiogram_windows
Project-URL: Issues, https://github.com/belyankiss/aiogram_windows/issues
Project-URL: Repository, https://github.com/belyankiss/aiogram_windows
